zack_liu_package1/__init__.py
zack_liu_package1/adminsite.py
zack_liu_package1-1.0.0.dist-info/LICENSE
zack_liu_package1-1.0.0.dist-info/METADATA
zack_liu_package1-1.0.0.dist-info/WHEEL
zack_liu_package1-1.0.0.dist-info/top_level.txt
zack_liu_package1-1.0.0.dist-info/RECORD
