Metadata-Version: 2.1
Name: zack_liu_package1
Version: 1.0.0
Summary: zack_zack_liu_package1package1
Home-page: https://github.com/liuzhimin2019/soho-ui.git
Author: 刘志敏
Author-email: liu.zhimin.2019@gmail.com
Classifier: Programming Language :: Python :: 3
Classifier: License :: OSI Approved :: MIT License
Classifier: Operating System :: OS Independent
Requires-Python: >=3.6
License-File: LICENSE
